orthogram/__init__.py
orthogram/__main__.py
orthogram/arrange/__init__.py
orthogram/arrange/label.py
orthogram/arrange/layout.py
orthogram/arrange/net.py
orthogram/arrange/refine.py
orthogram/arrange/route.py
orthogram/debug.py
orthogram/define/__init__.py
orthogram/define/attributes.py
orthogram/define/build.py
orthogram/define/defs.py
orthogram/define/diagram.py
orthogram/define/load.py
orthogram/draw/__init__.py
orthogram/draw/bands.py
orthogram/draw/blocks.py
orthogram/draw/boxes.py
orthogram/draw/connections.py
orthogram/draw/drawing.py
orthogram/draw/functions.py
orthogram/draw/grid.py
orthogram/draw/labels.py
orthogram/draw/shapes.py
orthogram/functions.py
orthogram/geometry.py
orthogram/util.py
orthogram-0.8.2.dist-info/LICENSE
orthogram-0.8.2.dist-info/WHEEL
orthogram-0.8.2.dist-info/METADATA
orthogram-0.8.2.dist-info/RECORD
