Metadata-Version: 2.1
Name: orthogram
Version: 0.8.2
Summary: Draw block diagrams.
Home-page: https://github.com/yorgath/orthogram
License: GPL-3.0-or-later
Keywords: block,diagram,graph
Author: Georgios Athanasiou
Author-email: yorgath@gmail.com
Maintainer: Georgios Athanasiou
Maintainer-email: yorgath@gmail.com
Requires-Python: >=3.8,<4.0
Classifier: Development Status :: 4 - Beta
Classifier: Environment :: Console
Classifier: License :: OSI Approved :: GNU General Public License v3 or later (GPLv3+)
Classifier: Programming Language :: Python :: 3
Classifier: Programming Language :: Python :: 3.10
Classifier: Programming Language :: Python :: 3.8
Classifier: Programming Language :: Python :: 3.9
Classifier: Topic :: Utilities
Requires-Dist: PyYAML (>=6.0,<7.0)
Requires-Dist: Shapely (>=1.8.2,<3)
Requires-Dist: cassowary (>=0.5.2,<0.6.0)
Requires-Dist: networkx (>=2.8.4,<3.0.0)
Requires-Dist: pycairo (==1.21.0)
Project-URL: Documentation, https://readthedocs.org/projects/orthogram/
Project-URL: Repository, https://github.com/yorgath/orthogram
